DEDLUtils/__init__.py
DEDLUtils/dedl_utilities.py
DEDLUtils/dt_utilities.py
dedlutils-0.0.4.dist-info/METADATA
dedlutils-0.0.4.dist-info/WHEEL
dedlutils-0.0.4.dist-info/licenses/LICENSE
dedlutils-0.0.4.dist-info/RECORD
